MANIFEST.in
setup.cfg
setup.py
meltingGeos/__init__.py
meltingGeos/meltingGeos.py
meltingGeos.egg-info/PKG-INFO
meltingGeos.egg-info/SOURCES.txt
meltingGeos.egg-info/dependency_links.txt
meltingGeos.egg-info/top_level.txt
meltingGeos/db/china.sqlite
meltingGeos/libgs/__init__.py
meltingGeos/libgs/db.py
meltingGeos/libgs/geos.py
meltingGeos/libgs/model.py