Metadata-Version: 1.0
Name: meltingGeos
Version: 0.0.4
Summary: Find standard city info names by obfuscated names;
Home-page: https://github.com/arrebole/meltingGeos
Author: arrebole
Author-email: concurrent.exec@gmail.com
License: UNKNOWN
Keywords: meltingGeos
Platform: UNKNOWN
